<?xml version="1.0" encoding="UTF-8"?>
<annotation_meta_data version="1.1">
    <source zoom_level="0">
        <region_of_interest offset_left="30208" offset_top="39680" width="13056" height="11264"/>
        <bounding_annotation name="Good14" color_bgr="FF0000" type="polygon" guid="{40B9BD30-D623-430C-8F96-7129375CD75A}">
            <p x="142" y="33"/><p x="142" y="11263"/><p x="12828" y="11263"/><p x="12828" y="33"/><p x="142" y="33"/>
        </bounding_annotation>
    </source>
    <destination micrometer_per_pixel_x="0.24328396570091901" micrometer_per_pixel_y="0.24328396570091901">
        <annotations>
            <annotation name="Good12" color_bgr="FF0000" type="polygon">
                <p x="-248" y="11075"/><p x="-248" y="14086"/><p x="11730" y="14086"/><p x="11730" y="11075"/><p x="-248" y="11075"/>
            </annotation>
        </annotations>
    </destination>
</annotation_meta_data>